xet_shard_parser-0.1.1.dist-info/METADATA
xet_shard_parser-0.1.1.dist-info/WHEEL
xet_shard_parser/__init__.py
xet_shard_parser/xet_shard_parser.cpython-312-x86_64-linux-gnu.so
xet_shard_parser-0.1.1.dist-info/RECORD
