Metadata-Version: 2.4
Name: xet_shard_parser
Version: 0.1.1
